[
  {
    "name": "USC Testnet 2",
    "base_url": "https://blockscout.usc-testnet2.creditcoin.network/",
    "rpc_url": "https://rpc.usc-testnet2.creditcoin.network",
    "accounts": [
      {
        "address": "0x44919C4B087B30d1afd7e58359604dE6fe986d8a",
        "name": "Testnet v2 faucet"
      },
      {
        "address": "0x3Cd0A705a2DC65e5b1E1205896BaA2be8A07c6e0",
        "name": "Testnet v2 query submitter"
      },
      {
        "address": "0x2C317383b8A99537c61042B63C4fB042Df51033a",
        "name": "NEW_LENDER_ accnt in 1Password. Used for testing"
      }
    ]
  },
  {
    "name": "USC Testnet 1",
    "base_url": "https://blockscout.usc-testnet.creditcoin.network/",
    "rpc_url": "https://rpc.usc-testnet.creditcoin.network",
    "accounts": [
      {
        "address": "0x0dfa236F82eB264183E568280609df16c6901D2D",
        "name": "Testnet v1 faucet"
      },
      {
        "address": "0x3Cd0A705a2DC65e5b1E1205896BaA2be8A07c6e0",
        "name": "Testnet v1 query submitter"
      }
    ]
  },
  {
    "name": "USC Devnet",
    "base_url": "https://blockscout.usc-devnet.creditcoin.network/",
    "rpc_url": "https://rpc.usc-devnet.creditcoin.network",
    "accounts": [
      {
        "address": "0x053e6100c1C9A31e5c8a56156649f0972dCC815e",
        "name": "Devnet bigbag"
      },
      {
        "address": "0x465ac26CD80E6e6AADe0C2EdfF2518D03Ac4E4e5",
        "name": "Devnet traffic sim"
      },
      {
        "address": "0x2C317383b8A99537c61042B63C4fB042Df51033a",
        "name": "NEW_LENDER_ accnt in 1Password. Used for testing"
      }
    ]
  }
]
